merge_pdf/__init__.py
merge_pdf/cli.py
merge_pdf/core.py
pdf_mergician-2025.12.3.1.dist-info/licenses/LICENSE
pdf_mergician-2025.12.3.1.dist-info/METADATA
pdf_mergician-2025.12.3.1.dist-info/WHEEL
pdf_mergician-2025.12.3.1.dist-info/entry_points.txt
pdf_mergician-2025.12.3.1.dist-info/top_level.txt
pdf_mergician-2025.12.3.1.dist-info/RECORD
