Metadata-Version: 2.4
Name: pdf-mergician
Version: 2025.12.3.1
Summary: A powerful CLI-first PDF merging and manipulation tool built on pypdf - like a magician for your PDFs!
Author-email: J McSwain <jmcswain@example.com>
License: MIT
Project-URL: Homepage, https://github.com/jmcswain/pdf-mergician
Project-URL: Documentation, https://github.com/jmcswain/pdf-mergician/tree/main/docs
Project-URL: Repository, https://github.com/jmcswain/pdf-mergician
Project-URL: Issues, https://github.com/jmcswain/pdf-mergician/issues
Keywords: pdf,merge,cli,pypdf,pdf-tools
Classifier: Development Status :: 4 - Beta
Classifier: Intended Audience :: Developers
Classifier: Intended Audience :: End Users/Desktop
Classifier: License :: OSI Approved :: MIT License
Classifier: Operating System :: OS Independent
Classifier: Programming Language :: Python :: 3
Classifier: Programming Language :: Python :: 3.8
Classifier: Programming Language :: Python :: 3.9
Classifier: Programming Language :: Python :: 3.10
Classifier: Programming Language :: Python :: 3.11
Classifier: Programming Language :: Python :: 3.12
Classifier: Topic :: Office/Business
Classifier: Topic :: Utilities
Requires-Python: >=3.8
License-File: LICENSE
Requires-Dist: pypdf>=4.0.0
Requires-Dist: click>=8.1.0
Provides-Extra: dev
Requires-Dist: pytest>=8.0.0; extra == "dev"
Requires-Dist: pytest-cov>=4.1.0; extra == "dev"
Requires-Dist: ruff>=0.4.0; extra == "dev"
Requires-Dist: build>=1.0.0; extra == "dev"
Requires-Dist: twine>=5.0.0; extra == "dev"
Dynamic: license-file
